forecast/AbstractModel.py
forecast/__init__.py
forecast/test_models.py
forecast/SeasonalityByAverageModel.py
common/test_vectorize.py
common/__init__.py
common/vectorize.py
sibyl-0.1.dist-info/RECORD
sibyl-0.1.dist-info/METADATA
sibyl-0.1.dist-info/top_level.txt
sibyl-0.1.dist-info/WHEEL
sibyl-0.1.dist-info/DESCRIPTION.rst
sibyl-0.1.dist-info/entry_points.txt
sibyl-0.1.dist-info/metadata.json
